asosoft/G2P.py
asosoft/Normalize.py
asosoft/Number2Word.py
asosoft/PoemClassifier.py
asosoft/Sort.py
asosoft/Transliteration.py
asosoft/__init__.py
asosoft/resources/G2PCertain.csv
asosoft/resources/G2PExceptions.csv
asosoft/resources/NormalizeUnicodeAdditional.csv
asosoft/resources/NormalizeUnicodeDeep.csv
asosoft/resources/Phoneme2Ascii.csv
asosoft/resources/Phoneme2IPA.csv
asosoft/resources/PoemPatterns.csv
asosoft-0.2.0.dist-info/LICENSE
asosoft-0.2.0.dist-info/METADATA
asosoft-0.2.0.dist-info/WHEEL
asosoft-0.2.0.dist-info/top_level.txt
asosoft-0.2.0.dist-info/RECORD
