Metadata-Version: 2.1
Name: asosoft
Version: 0.2.0
Summary: AsoSoft's Library for Kurdish language processing tasks
Home-page: https://github.com/AsoSoft/AsoSoft-Library-py
Author: Aso Mahmudi
Author-email: aso.mehmudi@gmail.com
License: MIT
Keywords: natural-language-processing,normalization,unicode-normalization,central-kurdish,kurdish,sorani
Classifier: License :: OSI Approved :: MIT License
Classifier: Programming Language :: Python :: 3.8
Classifier: Operating System :: OS Independent
Requires-Python: >=3.8
License-File: LICENSE
Requires-Dist: regex >=2023.0.0
Provides-Extra: dev
Requires-Dist: pytest >=7.0 ; extra == 'dev'
Requires-Dist: twine >=4.0.2 ; extra == 'dev'
